LICENSE
MANIFEST.in
README.rst
setup.py
cmdline_op_jul14_01.egg-info/PKG-INFO
cmdline_op_jul14_01.egg-info/SOURCES.txt
cmdline_op_jul14_01.egg-info/dependency_links.txt
cmdline_op_jul14_01.egg-info/entry_points.txt
cmdline_op_jul14_01.egg-info/top_level.txt
optimalprobes/__init__.py
optimalprobes/__main__.py
optimalprobes/bkp.tempgenerateSets.py
optimalprobes/calcContacts.py
optimalprobes/checkInputs.py
optimalprobes/dependencies.py
optimalprobes/exposedResidues.py
optimalprobes/generateConfigFile.py
optimalprobes/generateTrials.py
optimalprobes/help.py
optimalprobes/macros.py
optimalprobes/optimalprobes.py
optimalprobes/residueMapping.py
optimalprobes/scoreTrials.py
optimalprobes/tempgenerateSets.py
optimalprobes/topChoices.py
optimalprobes/writeOspreyConfig.py