Metadata-Version: 1.0
Name: cmdline-op-jul14-01
Version: 0.15.5
Summary: Python command line application for Optimal Probes.
Home-page: http://www.shuklagroup.org/
Author: Shriyaa Mittal
Author-email: mittalshriyaa@gmail.com
License: This is a license file.
